backend/app/models.py
backend/app/core/__init__.py
backend/app/core/simple_config.py
backend/app/services/document_agents.py
backend/app/services/local_storage_service.py
backend/app/services/openai_service.py
docforge/__init__.py
docforge/docforge.py
docforge_ai-2.0.3.dist-info/licenses/LICENSE
prompts/architecture.md
prompts/business_case.md
prompts/charter.md
prompts/deployment.md
prompts/design.md
prompts/market_requirements.md
prompts/operations.md
prompts/requirements.md
prompts/testing.md
prompts/vision_brief.md
docforge_ai-2.0.3.dist-info/METADATA
docforge_ai-2.0.3.dist-info/WHEEL
docforge_ai-2.0.3.dist-info/entry_points.txt
docforge_ai-2.0.3.dist-info/top_level.txt
docforge_ai-2.0.3.dist-info/RECORD
