Metadata-Version: 2.4
Name: docforge-ai
Version: 2.0.3
Summary: Self-contained AI-powered documentation generator
Home-page: https://github.com/Venkatesh188/docforge
Author: DocForge Community
Author-email: DocForge Community <community@docforge.dev>
Maintainer-email: DocForge Community <community@docforge.dev>
License-Expression: MIT
Project-URL: Homepage, https://github.com/Venkatesh188/docforge
Project-URL: Bug Reports, https://github.com/Venkatesh188/docforge/issues
Project-URL: Feature Requests, https://github.com/Venkatesh188/docforge/issues/new?template=feature_request.yml
Project-URL: Documentation, https://github.com/Venkatesh188/docforge/wiki
Project-URL: Source, https://github.com/Venkatesh188/docforge
Project-URL: PyPI, https://pypi.org/project/docforge-ai/
Keywords: documentation,ai,generator,automation,software-development,project-management,openai,markdown
Classifier: Development Status :: 4 - Beta
Classifier: Intended Audience :: Developers
Classifier: Topic :: Software Development :: Documentation
Classifier: Topic :: Text Processing :: Markup
Classifier: Programming Language :: Python :: 3
Classifier: Programming Language :: Python :: 3.10
Classifier: Programming Language :: Python :: 3.11
Classifier: Programming Language :: Python :: 3.12
Classifier: Programming Language :: Python :: 3.13
Classifier: Operating System :: OS Independent
Classifier: Environment :: Console
Requires-Python: >=3.10
License-File: LICENSE
Requires-Dist: openai<2.0.0,>=1.0.0
Requires-Dist: tiktoken>=0.6.0
Requires-Dist: pydantic<3.0.0,>=2.6.0
Requires-Dist: pydantic-settings>=2.0.0
Requires-Dist: python-dotenv>=1.0.0
Requires-Dist: PyYAML>=6.0.0
Requires-Dist: python-slugify>=8.0.0
Requires-Dist: httpx>=0.24.0
Requires-Dist: crewai>=0.141.0
Provides-Extra: dev
Requires-Dist: pytest>=7.0.0; extra == "dev"
Requires-Dist: pytest-asyncio>=0.21.0; extra == "dev"
Requires-Dist: black>=23.0.0; extra == "dev"
Requires-Dist: flake8>=6.0.0; extra == "dev"
Requires-Dist: mypy>=1.0.0; extra == "dev"
Dynamic: author
Dynamic: home-page
Dynamic: license-file
Dynamic: requires-python
